mcp_server_ebs/__init__.py
mcp_server_ebs/config.py
mcp_server_ebs/server.py
ebs_mcp_server-0.1.0.dist-info/METADATA
ebs_mcp_server-0.1.0.dist-info/WHEEL
ebs_mcp_server-0.1.0.dist-info/entry_points.txt
ebs_mcp_server-0.1.0.dist-info/top_level.txt
ebs_mcp_server-0.1.0.dist-info/RECORD
