Metadata-Version: 2.4
Name: ebs-mcp-server
Version: 0.1.0
Summary: Add your description here
Requires-Python: >=3.13
Requires-Dist: aiohttp>=3.11.18
Requires-Dist: deprecated>=1.2.18
Requires-Dist: mcp[cli]>=1.6.0
Requires-Dist: volcengine-python-sdk>=1.1.5
